nvdlib/__init__.py
nvdlib/classes.py
nvdlib/cpe.py
nvdlib/cve.py
nvdlib/get.py
nvdlib-0.8.2.dist-info/LICENSE
nvdlib-0.8.2.dist-info/METADATA
nvdlib-0.8.2.dist-info/WHEEL
nvdlib-0.8.2.dist-info/top_level.txt
nvdlib-0.8.2.dist-info/RECORD
