Metadata-Version: 2.2
Name: nvdlib
Version: 0.8.2
Summary: National Vulnerability Database CPE/CVE API Library for Python
Home-page: https://github.com/Vehemont/nvdlib/
Author: Vehemont
Author-email: brad@nvdlib.com
License: MIT
Requires-Python: >=3.11.0
License-File: LICENSE
Requires-Dist: requests
Provides-Extra: dev
Requires-Dist: responses==0.18.0; extra == "dev"
Requires-Dist: pytest==7.0.1; extra == "dev"
Dynamic: author
Dynamic: author-email
Dynamic: description
Dynamic: description-content-type
Dynamic: home-page
Dynamic: license
Dynamic: provides-extra
Dynamic: requires-dist
Dynamic: requires-python
Dynamic: summary
